Metadata-Version: 1.0
Name: stat-dist333
Version: 0.1
Summary: Statistical distributions - Gaussian, Binomial etc..
Home-page: UNKNOWN
Author: Amanpreet Singh
Author-email: amanpreetsingh459@gmail.com
License: UNKNOWN
Platform: UNKNOWN
